serverless_local_debugger/__init__.py
serverless_local_debugger/core/debugger.py
serverless_local_debugger-0.0.5.dist-info/LICENSE
serverless_local_debugger-0.0.5.dist-info/METADATA
serverless_local_debugger-0.0.5.dist-info/WHEEL
serverless_local_debugger-0.0.5.dist-info/top_level.txt
serverless_local_debugger-0.0.5.dist-info/RECORD
